LICENSE
README.md
pyproject.toml
setup.py
./imap/__init__.py
./imap/editor.py
./imap/global_var.py
./imap/main.py
./imap/map.py
./imap/lib/__init__.py
./imap/lib/common.py
./imap/lib/convertor.py
./imap/lib/convex_hull.py
./imap/lib/draw.py
./imap/lib/lane_manager.py
./imap/lib/odr_spiral.py
./imap/lib/polynoms.py
./imap/lib/proj_helper.py
./imap/lib/proto_utils.py
./imap/lib/transform.py
./imap/lib/opendrive/__init__.py
./imap/lib/opendrive/common.py
./imap/lib/opendrive/header.py
./imap/lib/opendrive/junction.py
./imap/lib/opendrive/lanes.py
./imap/lib/opendrive/map.py
./imap/lib/opendrive/plan_view.py
./imap/lib/opendrive/profile.py
./imap/lib/opendrive/road.py
./imap/lib/opendrive/signals.py
./imap/lib/opendrive/user_data.py
./modules/__init__.py
./modules/map/__init__.py
./modules/map/proto/__init__.py
./modules/map/proto/direction.proto
./modules/map/proto/direction_pb2.py
./modules/map/proto/drive_state.proto
./modules/map/proto/drive_state_pb2.py
./modules/map/proto/error_code.proto
./modules/map/proto/error_code_pb2.py
./modules/map/proto/geometry.proto
./modules/map/proto/geometry_pb2.py
./modules/map/proto/header.proto
./modules/map/proto/header_pb2.py
./modules/map/proto/map.proto
./modules/map/proto/map_clear_area.proto
./modules/map/proto/map_clear_area_pb2.py
./modules/map/proto/map_crosswalk.proto
./modules/map/proto/map_crosswalk_pb2.py
./modules/map/proto/map_geometry.proto
./modules/map/proto/map_geometry_pb2.py
./modules/map/proto/map_id.proto
./modules/map/proto/map_id_pb2.py
./modules/map/proto/map_junction.proto
./modules/map/proto/map_junction_pb2.py
./modules/map/proto/map_lane.proto
./modules/map/proto/map_lane_pb2.py
./modules/map/proto/map_overlap.proto
./modules/map/proto/map_overlap_pb2.py
./modules/map/proto/map_parking_space.proto
./modules/map/proto/map_parking_space_pb2.py
./modules/map/proto/map_pb2.py
./modules/map/proto/map_pnc_junction.proto
./modules/map/proto/map_pnc_junction_pb2.py
./modules/map/proto/map_road.proto
imap_test.egg-info/PKG-INFO
imap_test.egg-info/SOURCES.txt
imap_test.egg-info/dependency_links.txt
imap_test.egg-info/entry_points.txt
imap_test.egg-info/requires.txt
imap_test.egg-info/top_level.txt