Metadata-Version: 2.1
Name: imap_test
Version: 0.1.6.3
Summary: Apollo map and Opendrive map converter
Home-page: https://github.com/Jh271441/imap_test
Author: JunhaoChen
Author-email: 609752056@qq.com
Project-URL: Bug Tracker, https://github.com/Jh271441/imap_test/issues
Classifier: Programming Language :: Python :: 3
Classifier: License :: OSI Approved :: Apache Software License
Classifier: Operating System :: OS Independent
Requires-Python: >=3.6
License-File: LICENSE
Requires-Dist: protobuf<=3.19.4
Requires-Dist: matplotlib
Requires-Dist: pyproj
